clideps/__init__.py
clideps/errors.py
clideps/py.typed
clideps/cli/cli_commands.py
clideps/cli/cli_main.py
clideps/env_vars/__init__.py
clideps/env_vars/dotenv_setup.py
clideps/env_vars/dotenv_utils.py
clideps/env_vars/env_check.py
clideps/env_vars/env_enum.py
clideps/env_vars/env_names.py
clideps/pkgs/__init__.py
clideps/pkgs/common_pkg_checkers.py
clideps/pkgs/common_pkg_managers.py
clideps/pkgs/common_pkgs.yml
clideps/pkgs/install_suggestions.py
clideps/pkgs/pkg_check.py
clideps/pkgs/pkg_checker_registry.py
clideps/pkgs/pkg_info.py
clideps/pkgs/pkg_manager_check.py
clideps/pkgs/pkg_model.py
clideps/pkgs/pkg_types.py
clideps/pkgs/platform_checks.py
clideps/run/__init__.py
clideps/run/run_commands.py
clideps/terminal/osc_utils.py
clideps/terminal/terminal_features.py
clideps/terminal/terminal_images.py
clideps/ui/__init__.py
clideps/ui/inputs.py
clideps/ui/rich_output.py
clideps/ui/styles.py
clideps/utils/readable_argparse.py
clideps/utils/which_all.py
clideps-0.1.8.dist-info/METADATA
clideps-0.1.8.dist-info/WHEEL
clideps-0.1.8.dist-info/entry_points.txt
clideps-0.1.8.dist-info/licenses/LICENSE
clideps-0.1.8.dist-info/RECORD
