Metadata-Version: 2.4
Name: clideps
Version: 0.1.8
Summary: Terminal environment setup with less pain
Project-URL: Repository, https://github.com/jlevy/clideps
Author-email: Joshua Levy <joshua@cal.berkeley.edu>
License-Expression: MIT
License-File: LICENSE
Classifier: Development Status :: 4 - Beta
Classifier: Intended Audience :: Developers
Classifier: Operating System :: OS Independent
Classifier: Programming Language :: Python
Classifier: Programming Language :: Python :: 3
Classifier: Programming Language :: Python :: 3.11
Classifier: Programming Language :: Python :: 3.12
Classifier: Programming Language :: Python :: 3.13
Classifier: Programming Language :: Python :: 3.14
Classifier: Typing :: Typed
Requires-Python: <4.0,>=3.11
Requires-Dist: cachetools>=5.5.2
Requires-Dist: dotenv>=0.9.9
Requires-Dist: flowmark>=0.5.7
Requires-Dist: prettyfmt>=0.3.1
Requires-Dist: pydantic>=2.12.4
Requires-Dist: pyyaml>=6.0.2
Requires-Dist: questionary>=2.1.0
Requires-Dist: rich-argparse>=1.7.0
Requires-Dist: rich>=14.0.0
Requires-Dist: strif>=3.0.1
